empaquetadas/__init__.py
empaquetadas/cli.py
empaquetadas/samples.py
empaquetadas-0.0.5.dist-info/LICENSE
empaquetadas-0.0.5.dist-info/METADATA
empaquetadas-0.0.5.dist-info/WHEEL
empaquetadas-0.0.5.dist-info/entry_points.txt
empaquetadas-0.0.5.dist-info/top_level.txt
empaquetadas-0.0.5.dist-info/RECORD
