Metadata-Version: 2.1
Name: empaquetadas
Version: 0.0.5
Summary: Package to calculate what would have happened if you had invested your pesos
Author-email: Rafael Sanabria <rafael.d.sanabria@gmail.com>
License: MIT License
Requires-Python: >=3.9
License-File: LICENSE
Requires-Dist: click (>=8.1)
Provides-Extra: dev
Requires-Dist: pytest (>=7.3) ; extra == 'dev'
